mysqlhandler/__init__.py
mysqlhandler/mysql_handler.py
mysqlhandler/pymysql_handler.py
usss_mysqlhandler-0.2.15.dist-info/licenses/LICENSE
usss_mysqlhandler-0.2.15.dist-info/METADATA
usss_mysqlhandler-0.2.15.dist-info/WHEEL
usss_mysqlhandler-0.2.15.dist-info/top_level.txt
usss_mysqlhandler-0.2.15.dist-info/RECORD
