Metadata-Version: 2.4
Name: usss-mysqlhandler
Version: 0.2.15
Summary: MySQL convenience package 
Home-page: https://github.com/pypa/mysqlhandler
Author: Julian Briggs
Author-email: Julian Briggs <julian.briggs@sheffield.ac.uk>
License-Expression: MIT
Project-URL: Homepage, https://github.com/pypa/usss-mysqlhandler
Project-URL: Issues, https://github.com/pypa/usss-mysqlhandler/issues
Classifier: Programming Language :: Python :: 3
Classifier: Operating System :: OS Independent
Requires-Python: >=3.11
License-File: LICENSE
Provides-Extra: dev
Requires-Dist: pytest; extra == "dev"
Requires-Dist: mypy; extra == "dev"
Requires-Dist: pytest-mock; extra == "dev"
Requires-Dist: pytest-cov; extra == "dev"
Requires-Dist: types-pyyaml; extra == "dev"
Requires-Dist: unittest2pytest; extra == "dev"
Requires-Dist: pylint-pytest; extra == "dev"
Requires-Dist: build; extra == "dev"
Requires-Dist: twine; extra == "dev"
Provides-Extra: pymysql
Requires-Dist: pymysql[rsa]; extra == "pymysql"
Provides-Extra: mysqlconnector
Requires-Dist: mysql-connector-python; extra == "mysqlconnector"
Dynamic: license-file
